cryptostream/__init__.py
cryptostream-0.1.0.dist-info/METADATA
cryptostream-0.1.0.dist-info/RECORD
cryptostream-0.1.0.dist-info/WHEEL
cryptostream-0.1.0.dist-info/top_level.txt
