Metadata-Version: 2.1
Name: cryptostream
Version: 0.1.0
Summary: Stream data to multiple clients whilst respecting privacy of the data
Home-page: https://github.com/dayjaby/cryptostream
Author: David Jablonski
Author-email: dayjaby@gmail.com
License: UNKNOWN
Platform: UNKNOWN
Classifier: Programming Language :: Python
Classifier: License :: OSI Approved :: MIT License
Classifier: Operating System :: OS Independent
Requires-Dist: pycryptodome
